{
  "gizmos-infos": {
    "is2D": true,
    "is3DIcon": false,
    "iconSize": 2,
    "gridVisible": true,
    "gridColor": [
      166,
      166,
      166,
      255
    ],
    "transformToolName": "position",
    "pivot": "pivot",
    "coordinate": "local",
    "toolsVisibility3d": true
  },
  "__version__": "1.0.0",
  "builder": {},
  "snap-configs": {
    "position": {
      "x": 1,
      "y": 1,
      "z": 1
    },
    "rotation": 1,
    "scale": 1,
    "isPositionSnapEnabled": false,
    "isRotationSnapEnabled": false,
    "isScaleSnapEnabled": false
  },
  "rect-snap-configs": {
    "enableSnapping": true,
    "snapThreshold": 4
  },
  "float-window": {
    "position": {
      "cc": {
        "Camera": {
          "dock": false,
          "top": null,
          "bottom": 10,
          "left": null,
          "right": 10
        }
      }
    }
  },
  "camera-infos": {
    "18e39b92-66b3-46fb-8198-2fd4d0e346d4": {
      "position": {
        "x": 446.619116996256,
        "y": 723.1379717168878,
        "z": 5000
      },
      "rotation": {
        "x": 0,
        "y": 0,
        "z": 0,
        "w": 1
      },
      "viewCenter": {
        "x": 0,
        "y": 0,
        "z": 0
      },
      "contentRect": {
        "x": 160.82771758307558,
        "y": 580.2422720102976,
        "width": 420,
        "height": 210
      },
      "scale": 0.7348016785361492
    },
    "83b1ba08-a8ef-45e9-8f04-cd875e7a827b": {
      "position": {
        "x": 233.11999614699778,
        "y": 390.0067288486034,
        "z": 5000
      },
      "rotation": {
        "x": 0,
        "y": 0,
        "z": 0,
        "w": 1
      },
      "viewCenter": {
        "x": 0,
        "y": 0,
        "z": 0
      },
      "contentRect": {
        "x": -217.1696891321497,
        "y": 98.26974965366283,
        "width": 1248.8,
        "height": 884.8
      },
      "scale": 1.324480705415836
    }
  },
  "camera-uuids": [
    "18e39b92-66b3-46fb-8198-2fd4d0e346d4",
    "83b1ba08-a8ef-45e9-8f04-cd875e7a827b"
  ],
  "camera": {
    "color": [
      48,
      48,
      48,
      255
    ],
    "fov": 45,
    "far": 10000,
    "near": 0.01,
    "wheelSpeed": 0.01,
    "wanderSpeed": 10,
    "enableAcceleration": true,
    "size": "__default_design__",
    "far2D": 10000,
    "near2D": 1,
    "wheelSpeed2D": 6,
    "iso": 0,
    "aperture": 19,
    "shutter": 7
  }
}
